reinforceui_studio/__init__.py
reinforceui_studio/main.py
reinforceui_studio/GUI/__init__.py
reinforceui_studio/GUI/load_model_window.py
reinforceui_studio/GUI/select_algorithm_window.py
reinforceui_studio/GUI/select_environment_window.py
reinforceui_studio/GUI/select_hyperparameters_window.py
reinforceui_studio/GUI/select_multiple_algorithm_window.py
reinforceui_studio/GUI/select_platform_window.py
reinforceui_studio/GUI/training_window.py
reinforceui_studio/GUI/ui_base_window.py
reinforceui_studio/GUI/ui_styles.py
reinforceui_studio/GUI/ui_utils.py
reinforceui_studio/GUI/welcome_window.py
reinforceui_studio/GUI/icons/__init__.py
reinforceui_studio/GUI/icons/back.svg
reinforceui_studio/GUI/icons/cheetah_run.gif
reinforceui_studio/GUI/icons/comparative_icon.svg
reinforceui_studio/GUI/icons/config.svg
reinforceui_studio/GUI/icons/half_cheetah.gif
reinforceui_studio/GUI/icons/load_icon.svg
reinforceui_studio/GUI/icons/pendulum.gif
reinforceui_studio/GUI/icons/single_icon.svg
reinforceui_studio/RL_algorithms/__init__.py
reinforceui_studio/RL_algorithms/CTD4/CTD4.py
reinforceui_studio/RL_algorithms/CTD4/__init__.py
reinforceui_studio/RL_algorithms/CTD4/networks/__init__.py
reinforceui_studio/RL_algorithms/CTD4/networks/actor.py
reinforceui_studio/RL_algorithms/CTD4/networks/critic.py
reinforceui_studio/RL_algorithms/DDPG/DDPG.py
reinforceui_studio/RL_algorithms/DDPG/__init__.py
reinforceui_studio/RL_algorithms/DDPG/networks/__init__.py
reinforceui_studio/RL_algorithms/DDPG/networks/actor.py
reinforceui_studio/RL_algorithms/DDPG/networks/critic.py
reinforceui_studio/RL_algorithms/DQN/DQN.py
reinforceui_studio/RL_algorithms/DQN/__init__.py
reinforceui_studio/RL_algorithms/DQN/networks/__init__.py
reinforceui_studio/RL_algorithms/DQN/networks/network.py
reinforceui_studio/RL_algorithms/PPO/PPO.py
reinforceui_studio/RL_algorithms/PPO/__init__.py
reinforceui_studio/RL_algorithms/PPO/networks/__init__.py
reinforceui_studio/RL_algorithms/PPO/networks/actor.py
reinforceui_studio-1.3.3.dist-info/licenses/LICENSE
reinforceui_studio-1.3.3.dist-info/METADATA
reinforceui_studio-1.3.3.dist-info/WHEEL
reinforceui_studio-1.3.3.dist-info/entry_points.txt
reinforceui_studio-1.3.3.dist-info/top_level.txt
reinforceui_studio-1.3.3.dist-info/RECORD
