Metadata-Version: 2.4
Name: reinforceui-studio
Version: 1.3.3
Summary: A GUI to simplify the configuration and monitoring of RL training processes.
Home-page: https://github.com/dvalenciar/ReinforceUI-Studio
Author: David Valencia
Author-email: support@reinforceui-studio.com
License: MIT
Project-URL: Documentation, https://docs.reinforceui-studio.com
Project-URL: Repository, https://github.com/dvalenciar/ReinforceUI-Studio
Project-URL: Tracker, https://github.com/dvalenciar/ReinforceUI-Studio/issues
Keywords: reinforcement-learning machine-learning deep-learning GUI
Classifier: Programming Language :: Python :: 3
Classifier: License :: OSI Approved :: MIT License
Classifier: Operating System :: OS Independent
Classifier: Intended Audience :: Developers
Classifier: Intended Audience :: Education
Classifier: Intended Audience :: Science/Research
Classifier: Topic :: Scientific/Engineering :: Artificial Intelligence
Classifier: Environment :: X11 Applications :: Qt
Requires-Python: >=3.10
License-File: LICENSE
Requires-Dist: PyYAML~=6.0.2
Requires-Dist: setuptools~=80.9.0
Requires-Dist: PyQt5~=5.15.11
Requires-Dist: matplotlib~=3.9.4
Requires-Dist: pandas~=2.2.3
Requires-Dist: numpy~=1.26.4
Requires-Dist: torch~=2.7.1
Requires-Dist: seaborn~=0.13.2
Requires-Dist: mlflow~=3.1.0
Requires-Dist: mlflow-skinny~=3.1.0
Requires-Dist: gymnasium~=1.1.1
Requires-Dist: gymnasium[classic-control]~=1.1.1
Requires-Dist: gymnasium[box2d]~=1.1.1
Requires-Dist: dm_control~=1.0.30
Requires-Dist: swig~=4.3.0
Requires-Dist: imageio~=2.37.0
Requires-Dist: opencv-python-headless~=4.10.0
Dynamic: author
Dynamic: author-email
Dynamic: classifier
Dynamic: description
Dynamic: description-content-type
Dynamic: home-page
Dynamic: keywords
Dynamic: license
Dynamic: license-file
Dynamic: project-url
Dynamic: requires-dist
Dynamic: requires-python
Dynamic: summary
